[
    {
        "code": "6942",
        "url": "https://fusionsid.xyz"
    },
    {
        "code": "4269",
        "url": "https://google.com"
    },
    {
        "code": "9TJx",
        "url": "http://microsoft.com"
    },
    {
        "code": "C5pc",
        "url": "http://microsoft.com"
    },
    {
        "code": "xNg1",
        "url": "http://microsoft.com"
    },
    {
        "code": "x5CN",
        "url": "http://microsoft.com"
    },
    {
        "code": "kBH6",
        "url": "http://microsoft.com"
    },
    {
        "code": "2EmH",
        "url": "http://microsoft.com"
    },
    {
        "code": "I3ws",
        "url": "http://microsoft.com"
    },
    {
        "code": "u53G",
        "url": "http://microsoft.com"
    },
    {
        "code": "9iDM",
        "url": "http://microsoft.com"
    },
    {
        "code": "qD3O",
        "url": "http://microsoft.com"
    },
    {
        "code": "s8Ou",
        "url": "http://microsoft.com"
    },
    {
        "code": "uYv0",
        "url": "http://microsoft.com"
    },
    {
        "code": "Vd51",
        "url": "http://microsoft.com"
    },
    {
        "code": "dVK5",
        "url": "http://microsoft.com"
    },
    {
        "code": "R4cJ",
        "url": "http://microsoft.com"
    },
    {
        "code": "7sA6",
        "url": "http://microsoft.com"
    },
    {
        "code": "S3nO",
        "url": "http://microsoft.com"
    }
]